odoo/addons/partner_grandchildren_access_link/README.rst
odoo/addons/partner_grandchildren_access_link/__init__.py
odoo/addons/partner_grandchildren_access_link/__manifest__.py
odoo/addons/partner_grandchildren_access_link/i18n/es.po
odoo/addons/partner_grandchildren_access_link/readme/CONTRIBUTORS.md
odoo/addons/partner_grandchildren_access_link/readme/DESCRIPTION.md
odoo/addons/partner_grandchildren_access_link/readme/USAGE.md
odoo/addons/partner_grandchildren_access_link/static/description/icon.png
odoo/addons/partner_grandchildren_access_link/static/description/index.html
odoo/addons/partner_grandchildren_access_link/views/res_partner.xml
odoo_addon_partner_grandchildren_access_link-17.0.1.0.0.1.dist-info/METADATA
odoo_addon_partner_grandchildren_access_link-17.0.1.0.0.1.dist-info/WHEEL
odoo_addon_partner_grandchildren_access_link-17.0.1.0.0.1.dist-info/top_level.txt
odoo_addon_partner_grandchildren_access_link-17.0.1.0.0.1.dist-info/RECORD
